README.md
setup.cfg
setup.py
dis_sdk_python/__init__.py
dis_sdk_python/com/__init__.py
dis_sdk_python/com/huaweicloud/__init__.py
dis_sdk_python/com/huaweicloud/dis/__init__.py
dis_sdk_python/com/huaweicloud/dis/sdk/__init__.py
dis_sdk_python/com/huaweicloud/dis/sdk/python/__init__.py
dis_sdk_python/com/huaweicloud/dis/sdk/python/client/__init__.py
dis_sdk_python/com/huaweicloud/dis/sdk/python/client/disclient.py
dis_sdk_python/com/huaweicloud/dis/sdk/python/models/DumpTask.py
dis_sdk_python/com/huaweicloud/dis/sdk/python/models/__init__.py
dis_sdk_python/com/huaweicloud/dis/sdk/python/models/base_model.py
dis_sdk_python/com/huaweicloud/dis/sdk/python/models/disauth.py
dis_sdk_python/com/huaweicloud/dis/sdk/python/models/disexception.py
dis_sdk_python/com/huaweicloud/dis/sdk/python/models/disrequest.py
dis_sdk_python/com/huaweicloud/dis/sdk/python/models/log.py
dis_sdk_python/com/huaweicloud/dis/sdk/python/models/model_python2.py
dis_sdk_python/com/huaweicloud/dis/sdk/python/models/model_python3.py
dis_sdk_python/com/huaweicloud/dis/sdk/python/proto/__init__.py
dis_sdk_python/com/huaweicloud/dis/sdk/python/proto/record_pb2.py
dis_sdk_python/com/huaweicloud/dis/sdk/python/response/__init__.py
dis_sdk_python/com/huaweicloud/dis/sdk/python/response/disAppresonse.py
dis_sdk_python/com/huaweicloud/dis/sdk/python/response/disConsumeresponse.py
dis_sdk_python/com/huaweicloud/dis/sdk/python/response/disGetresponse.py
dis_sdk_python/com/huaweicloud/dis/sdk/python/response/disMonitorresponse.py
dis_sdk_python/com/huaweicloud/dis/sdk/python/response/disStreamresponse.py
dis_sdk_python/com/huaweicloud/dis/sdk/python/response/disadminresponse.py
dis_sdk_python/com/huaweicloud/dis/sdk/python/response/discheckpointresponse.py
dis_sdk_python/com/huaweicloud/dis/sdk/python/response/disreadDISConfig.py
dis_sdk_python/com/huaweicloud/dis/sdk/python/response/disrecordresponse.py
dis_sdk_python/com/huaweicloud/dis/sdk/python/response/disresponse.py
huaweicloud_python_sdk_dis.egg-info/PKG-INFO
huaweicloud_python_sdk_dis.egg-info/SOURCES.txt
huaweicloud_python_sdk_dis.egg-info/dependency_links.txt
huaweicloud_python_sdk_dis.egg-info/not-zip-safe
huaweicloud_python_sdk_dis.egg-info/requires.txt
huaweicloud_python_sdk_dis.egg-info/top_level.txt