Metadata-Version: 1.1
Name: huaweicloud-python-sdk-dis
Version: 2.0.2
Summary: Huawei Cloud DIS SDK for Python
Home-page: https://github.com/huaweicloud/huaweicloud-sdk-python-dis
Author: Huawei
Author-email: UNKNOWN
License: Apache-2.0
Keywords: dis,python
Platform: UNKNOWN
Classifier: Operating System :: POSIX :: Linux
Classifier: Programming Language :: Python :: 2.6
Classifier: Programming Language :: Python :: 2.7
Classifier: Programming Language :: Python :: 3
Classifier: Programming Language :: Python :: 3.3
Classifier: Programming Language :: Python :: 3.4
Classifier: Programming Language :: Python :: 3.5
